ezmq/.git/COMMIT_EDITMSG
ezmq/.git/config
ezmq/.git/description
ezmq/.git/FETCH_HEAD
ezmq/.git/HEAD
ezmq/.git/hooks/applypatch-msg.sample
ezmq/.git/hooks/commit-msg.sample
ezmq/.git/hooks/fsmonitor-watchman.sample
ezmq/.git/hooks/post-update.sample
ezmq/.git/hooks/pre-applypatch.sample
ezmq/.git/hooks/pre-commit.sample
ezmq/.git/hooks/pre-merge-commit.sample
ezmq/.git/hooks/pre-push.sample
ezmq/.git/hooks/pre-rebase.sample
ezmq/.git/hooks/pre-receive.sample
ezmq/.git/hooks/prepare-commit-msg.sample
ezmq/.git/hooks/push-to-checkout.sample
ezmq/.git/hooks/sendemail-validate.sample
ezmq/.git/hooks/update.sample
ezmq/.git/index
ezmq/.git/info/exclude
ezmq/.git/logs/HEAD
ezmq/.git/logs/refs/heads/master
ezmq/.git/logs/refs/heads/priority-queue
ezmq/.git/logs/refs/remotes/origin/HEAD
ezmq/.git/logs/refs/remotes/origin/master
ezmq/.git/logs/refs/remotes/origin/priority-queue
ezmq/.git/objects/00/36b235553422be07c172ad2fd0942c9cd966d6
ezmq/.git/objects/02/78c0682fb87d5233c73cf23439561f49e73444
ezmq/.git/objects/04/5608542b55bb1e4615e0f09f406c1e1aa9e533
ezmq/.git/objects/05/68aaa2efe7840a78f5a6962abd2b9692166fc9
ezmq/.git/objects/06/0d8f98c8fa1bfe8cee7502441f783965427808
ezmq/.git/objects/06/da3d1099d92ad78d5f2653c2881e86c6f4ccff
ezmq/.git/objects/0e/a537e1fc5e669139997d897455b137f9f3e406
ezmq/.git/objects/0f/02b79eec605442fea9473378d9a5ff699a0363
ezmq/.git/objects/10/13b216610dc46ea3d4d579dd307e04e7aab122
ezmq/.git/objects/10/b67a2940ff97c4742d40ffcb804176f7d8e1f8
ezmq/.git/objects/13/c0194b9372308c748b7cd1cbafeeb111e1e676
ezmq/.git/objects/14/0c212cbac864f25aed30d1d5d1f7998dc51af8
ezmq/.git/objects/14/abe625628dc762c6f8ea0acf9efa0d3a149215
ezmq/.git/objects/17/a0850a4ff93ac45f6374b36586a0c37549fcdb
ezmq/.git/objects/17/e8de97f0c07b0e79a9c16473823e2819a37ce4
ezmq/.git/objects/21/7390f8247f6c69f52a6c839f3010b83f4982ea
ezmq/.git/objects/27/f46d0ccb901e2c3aba08773c3e93e32cb00c23
ezmq/.git/objects/2b/9f7a568091738c3ebf558fcdb1940c7299a908
ezmq-2025.12.4.0.dist-info/METADATA
ezmq-2025.12.4.0.dist-info/WHEEL
ezmq-2025.12.4.0.dist-info/RECORD
