Metadata-Version: 2.4
Name: ezmq
Version: 2025.12.4.0
Summary: 
License: MIT
Author: Miles Copeland Luce
Requires-Python: >=3.13
Classifier: License :: OSI Approved :: MIT License
Classifier: Programming Language :: Python :: 3
Classifier: Programming Language :: Python :: 3.13
Classifier: Programming Language :: Python :: 3.14
Requires-Dist: fastparquet (>=2024.11.0,<2025.0.0)
Requires-Dist: openpyxl (>=3.1.5,<4.0.0)
Requires-Dist: pandas (>=2.3.3,<3.0.0)
